finder/VERSION
finder/__init__.py
finder/cmdline.py
finder/daemon.py
finder/server.py
finder/utils.py
finder/static/favicon.png
finder/static/jquery-1.12.1.min.js
finder/static/jquery.qrcode.min.js
finder/static/bootstrap/css/bootstrap-theme.css
finder/static/bootstrap/css/bootstrap-theme.css.map
finder/static/bootstrap/css/bootstrap-theme.min.css
finder/static/bootstrap/css/bootstrap-theme.min.css.map
finder/static/bootstrap/css/bootstrap.css
finder/static/bootstrap/css/bootstrap.css.map
finder/static/bootstrap/css/bootstrap.min.css
finder/static/bootstrap/css/bootstrap.min.css.map
finder/static/bootstrap/fonts/glyphicons-halflings-regular.eot
finder/static/bootstrap/fonts/glyphicons-halflings-regular.svg
finder/static/bootstrap/fonts/glyphicons-halflings-regular.ttf
finder/static/bootstrap/fonts/glyphicons-halflings-regular.woff
finder/static/bootstrap/fonts/glyphicons-halflings-regular.woff2
finder/static/bootstrap/js/bootstrap.js
finder/static/bootstrap/js/bootstrap.min.js
finder/static/bootstrap/js/npm.js
finder/static/dialog/css/bootstrap-dialog.css
finder/static/dialog/css/bootstrap-dialog.min.css
finder/static/dialog/js/bootstrap-dialog.js
finder/static/dialog/js/bootstrap-dialog.min.js
finder/static/dialog/less/bootstrap-dialog.less
finder/static/dropzone/basic.css
finder/static/dropzone/dropzone-amd-module.js
finder/static/dropzone/dropzone.css
finder/static/dropzone/dropzone.js
finder/templates/index.html
finder/templates/layout.html
finder/templates/upload.html
finder/zipstream/__init__.py
finder/zipstream/compat.py
finder_py-1.3.3.dist-info/METADATA
finder_py-1.3.3.dist-info/RECORD
finder_py-1.3.3.dist-info/WHEEL
finder_py-1.3.3.dist-info/entry_points.txt
finder_py-1.3.3.dist-info/top_level.txt
