Metadata-Version: 2.1
Name: finder-py
Version: 1.3.3
Summary: LAN file sharing
Home-page: https://github.com/hyxf/finder-py
Author: hyxf
Author-email: 1162584980@qq.com
License: Apache 2.0
Platform: UNKNOWN
Classifier: Topic :: Utilities
Classifier: Programming Language :: Python :: 2
Classifier: Programming Language :: Python :: 3
Classifier: License :: OSI Approved :: MIT License
Classifier: Operating System :: OS Independent
Requires-Python: >=2.7.*
Requires-Dist: qrcode
Requires-Dist: flask
